README.md
setup.cfg
setup.py
flake8_obey_import_goat/__init__.py
flake8_obey_import_goat/ast_tools.py
flake8_obey_import_goat/checker.py
flake8_obey_import_goat/custom_types.py
flake8_obey_import_goat/pathes.py
flake8_obey_import_goat/rules.py
flake8_obey_import_goat.egg-info/PKG-INFO
flake8_obey_import_goat.egg-info/SOURCES.txt
flake8_obey_import_goat.egg-info/dependency_links.txt
flake8_obey_import_goat.egg-info/entry_points.txt
flake8_obey_import_goat.egg-info/not-zip-safe
flake8_obey_import_goat.egg-info/requires.txt
flake8_obey_import_goat.egg-info/top_level.txt