Metadata-Version: 2.1
Name: flake8-obey-import-goat
Version: 0.1.1
Summary: An extension for flake8 that forbids some imports statements in some modules.
Home-page: https://github.com/Melevir/flake8-obey-import-goat
Author: Ilya Lebedev
Author-email: melevir@gmail.com
License: MIT
Keywords: flake8
Platform: UNKNOWN
Classifier: Environment :: Console
Classifier: Framework :: Flake8
Classifier: Operating System :: OS Independent
Classifier: Topic :: Software Development :: Documentation
Classifier: Topic :: Software Development :: Libraries :: Python Modules
Classifier: Topic :: Software Development :: Quality Assurance
Classifier: Programming Language :: Python
Classifier: Programming Language :: Python :: 3.9
Classifier: Programming Language :: Python :: 3.10
Requires-Python: >=3.9
